Workbook

Sheet Expense Summary
A1: GHANASHI – BUSINESS EXPENSE SUMMARY
A2: Edit the blue input cells if any quantity or expense changes.
A4: Expense | B4: Amount (₹) | C4: Quantity / units | D4: Cost per unit (₹)
A5: Product purchase cost (90 products) | B5: 11000 | C5: 90 | D5: =B5/C5
A6: Delivery / inward transport charge | B6: 500 | C6: 90 | D6: =B6/C6
A7: Bubble wrapper | B7: 184 | C7: 90 | D7: =B7/C7
A8: Packing bags (25 pieces) | B8: 179 | C8: 25 | D8: =B8/C8
A9: Cardboard boxes (25 pieces) | B9: 250 | C9: 25 | D9: =B9/C9
A10: Tape | B10: 50 | C10: 90 | D10: =B10/C10
A11: Miscellaneous | B11: 200 | C11: 90 | D11: =B11/C11
A13: TOTAL CASH EXPENSES | B13: =SUM(B5:B11)
A14: Average product purchase cost per product | B14: =B5/C5
A15: Total number of products | B15: =C5
A16: Note | B16: Packing bags and cardboard boxes are entered as 25 pieces each. This means these supplies currently cover only 25 orders if one of each is used per order.

Sheet Meesho Profit Calculator
A1: MEESHO SETTLEMENT & PROFIT CALCULATOR
A2: Settlement amounts below are transcribed from your Meesho screenshot. Update them from the latest pricing screen.
A3: Average cost allocation uses 90 products. Packing bag and box cost per used piece is based on 25 pieces purchased.
A5: Product | B5: Meesho customer price (₹) | C5: Meesho bank transfer (₹) | D5: Product cost / unit (₹) | E5: Shared cost / unit (₹) | F5: Bag + box / order (₹) | G5: Total estimated cost (₹) | H5: Estimated profit (₹) | I5: Profit margin on transfer | J5: Break-even transfer (₹)
A6: Wild Animal Puzzle | B6: 248 | C6: 190 | D6: ='Expense Summary'!$B$5/'Expense Summary'!$C$5 | E6: =SUM('Expense Summary'!$B$6,'Expense Summary'!$B$7,'Expense Summary'!$B$10,'Expense Summary'!$B$11)/'Expense Summary'!$C$5 | F6: ='Expense Summary'!$D$8+'Expense Summary'!$D$9 | G6: =SUM(D6:F6) | H6: =C6-G6 | I6: =IFERROR(H6/C6,0) | J6: =G6
A7: Vegetable Puzzle | B7: 159 | C7: 105 | D7: ='Expense Summary'!$B$5/'Expense Summary'!$C$5 | E7: =SUM('Expense Summary'!$B$6,'Expense Summary'!$B$7,'Expense Summary'!$B$10,'Expense Summary'!$B$11)/'Expense Summary'!$C$5 | F7: ='Expense Summary'!$D$8+'Expense Summary'!$D$9 | G7: =SUM(D7:F7) | H7: =C7-G7 | I7: =IFERROR(H7/C7,0) | J7: =G7
A8: Shapes Puzzle | B8: 173 | C8: 117 | D8: ='Expense Summary'!$B$5/'Expense Summary'!$C$5 | E8: =SUM('Expense Summary'!$B$6,'Expense Summary'!$B$7,'Expense Summary'!$B$10,'Expense Summary'!$B$11)/'Expense Summary'!$C$5 | F8: ='Expense Summary'!$D$8+'Expense Summary'!$D$9 | G8: =SUM(D8:F8) | H8: =C8-G8 | I8: =IFERROR(H8/C8,0) | J8: =G8
A9: Educational Puzzle | B9: 215 | C9: 160 | D9: ='Expense Summary'!$B$5/'Expense Summary'!$C$5 | E9: =SUM('Expense Summary'!$B$6,'Expense Summary'!$B$7,'Expense Summary'!$B$10,'Expense Summary'!$B$11)/'Expense Summary'!$C$5 | F9: ='Expense Summary'!$D$8+'Expense Summary'!$D$9 | G9: =SUM(D9:F9) | H9: =C9-G9 | I9: =IFERROR(H9/C9,0) | J9: =G9
A12: TOTAL EXPENSES PAID | B12: ='Expense Summary'!B13
A13: Estimated cost per packed order | B13: =G6
A14: Important assumption | B14: This calculator uses the average purchase cost (₹11,000 ÷ 90) for every product. Actual product costs may differ. It assumes one bag and one box per order; bag and box costs are ₹179 ÷ 25 and ₹250 ÷ 25 respectively. Confirm whether the ₹500 delivery charge is inward transport or customer delivery.
